{"$schema":"https://json-schema.org/draft/2020-12/schema","$id":"user-question.schema.json","type":"object","additionalProperties":false,"required":["id","userId","condition","topicId","postId","text","source","createdAt","extractedConceptIds"],"properties":{"id":{"type":"string","minLength":1,"maxLength":128},"userId":{"type":"string","minLength":1,"maxLength":128},"condition":{"enum":["control","experimental"]},"topicId":{"type":"string","minLength":1,"maxLength":128},"postId":{"type":"string","minLength":1,"maxLength":128},"text":{"type":"string","minLength":1,"maxLength":2000},"source":{"enum":["typed","suggested_question"]},"suggestedQuestionId":{"type":"string","minLength":1,"maxLength":128},"createdAt":{"type":"string","format":"date-time"},"extractedConceptIds":{"type":"array","items":{"type":"string","minLength":1,"maxLength":128},"uniqueItems":true,"maxItems":500},"extractedClaimIds":{"type":"array","items":{"type":"string","minLength":1,"maxLength":128},"uniqueItems":true,"maxItems":500},"questionType":{"type":"string","minLength":1,"maxLength":120},"unresolved":{"type":"boolean"},"aiAnswerId":{"type":"string","minLength":1,"maxLength":128}}}
